etiq_copilot.cpython-311-darwin.so
etiq_copilot.pyi
etiq_copilot/core/db/migrations/20230615-hello-migration.sql
etiq_copilot/core/sample_data/adult_data_sampled.csv
etiq_copilot/core/sample_data/adult_data_sampled.pkl
etiq_copilot/core/sample_data/adult_protected_train_resampled.pkl
etiq_copilot/core/sample_data/adult_x_train_resampled.pkl
etiq_copilot/core/sample_data/adult_y_train_resampled.pkl
etiq_copilot/core/sample_data/adultdata.pkl
etiq_copilot/core/sample_data/adultdataset.csv
etiq_copilot/core/sample_data/encoded_adult.csv
etiq_copilot/core/sample_data/encoded_adult.pkl
etiq_copilot/data/agent/system_prompt.yml
etiq_copilot/engine/rca/rca_config.schema.json
etiq_copilot/engine/rca/config/categorical_data_rca.json
etiq_copilot/engine/rca/config/distribution_differences_rca.json
etiq_copilot/engine/rca/config/etiq_scans_rca.json
etiq_copilot/engine/rca/config/mixed_datatypes_rca.json
etiq_copilot/engine/rca/config/scan_duplicates_rca.json
etiq_copilot/engine/test_pool/config/categorical_data.json
etiq_copilot/engine/test_pool/config/distribution_differences.json
etiq_copilot/engine/test_pool/config/etiq_data_issues_config.json
etiq_copilot/engine/test_pool/config/etiq_scans.json
etiq_copilot/engine/test_pool/config/etiq_univariate_tests.json
etiq_copilot/engine/test_pool/config/great_expectations_config.json
etiq_copilot/engine/test_pool/config/mixed_datatypes.json
etiq_copilot-2.2.3.dist-info/licenses/LICENSE
etiq_copilot-2.2.3.dist-info/METADATA
etiq_copilot-2.2.3.dist-info/WHEEL
etiq_copilot-2.2.3.dist-info/entry_points.txt
etiq_copilot-2.2.3.dist-info/top_level.txt
etiq_copilot-2.2.3.dist-info/RECORD
