Metadata-Version: 2.4
Name: etiq_copilot
Version: 2.2.3
Summary: Add your description here
Project-URL: Docs, https://docs.etiq.ai/
Project-URL: homepage, https://etiq.ai
Requires-Python: >=3.10
License-File: LICENSE
Requires-Dist: astroid>=3.3.11
Requires-Dist: eval-type-backport>=0.2.2; python_full_version < "3.10"
Requires-Dist: networkx>=3.2.1
Requires-Dist: niaarm>=0.4.3
Requires-Dist: pandas>=2.3.1
Requires-Dist: platformdirs>=4.3.8
Requires-Dist: pydantic>=2.11.7
Requires-Dist: pydot>=4.0.1
Requires-Dist: pyzmq>=27.0.0
Requires-Dist: semver>=3.0.4
Requires-Dist: shortuuid>=1.0.13
Requires-Dist: statsmodels>=0.14.5
Requires-Dist: typing-extensions>=4.14.1
Requires-Dist: sqlalchemy>=2.0.42
Requires-Dist: tabulate==0.9.0
Requires-Dist: requests>=2.32.4
Requires-Dist: pydantic-ai==1.0.13
Requires-Dist: xxhash>=3.5.0
Requires-Dist: pyflakes>=3.4.0
Requires-Dist: python-dotenv>=1.2.0
Provides-Extra: polars
Requires-Dist: polars>=1.31.0; extra == "polars"
Provides-Extra: ollama
Requires-Dist: langchain-ollama>=0.3.6; extra == "ollama"
Provides-Extra: pyspark
Requires-Dist: pyspark>=4.0.0; extra == "pyspark"
Provides-Extra: openai
Requires-Dist: langchain-openai>=0.3.28; extra == "openai"
Provides-Extra: google-genai
Requires-Dist: langchain-google-genai>=2.1.8; extra == "google-genai"
Dynamic: license-file
